Products.EasyNewsletter-5.0.11-nspkg.pth
Products/EasyNewsletter/__init__.py
Products/EasyNewsletter/config.py
Products/EasyNewsletter/configure.zcml
Products/EasyNewsletter/doi18ndude
Products/EasyNewsletter/doi18ndude-singlelang
Products/EasyNewsletter/enl_registration_tool.py
Products/EasyNewsletter/indexers.py
Products/EasyNewsletter/indexers.zcml
Products/EasyNewsletter/interfaces.py
Products/EasyNewsletter/issuedatafetcher.py
Products/EasyNewsletter/permissions.zcml
Products/EasyNewsletter/profiles.zcml
Products/EasyNewsletter/setuphandlers.py
Products/EasyNewsletter/subscriber.py
Products/EasyNewsletter/testing.py
Products/EasyNewsletter/upgrades.zcml
Products/EasyNewsletter/behaviors/__init__.py
Products/EasyNewsletter/behaviors/collection_as_newsletter_aggregation_source.py
Products/EasyNewsletter/behaviors/configure.zcml
Products/EasyNewsletter/behaviors/configure.zcml.example
Products/EasyNewsletter/behaviors/external_delivery_service.py
Products/EasyNewsletter/behaviors/external_delivery_service.py~Stashed changes
Products/EasyNewsletter/behaviors/external_subscriber_sources.py
Products/EasyNewsletter/behaviors/external_subscriber_sources.py~Stashed changes
Products/EasyNewsletter/behaviors/plone_user_group_recipients.py
Products/EasyNewsletter/browser/__init__.py
Products/EasyNewsletter/browser/actions_menu.py
Products/EasyNewsletter/browser/all_issues_view.pt
Products/EasyNewsletter/browser/configure.zcml
Products/EasyNewsletter/browser/controlpanel.py
Products/EasyNewsletter/browser/daily_issue.py
Products/EasyNewsletter/browser/edithelper.py
Products/EasyNewsletter/browser/enl_subscribers_view.pt
Products/EasyNewsletter/browser/helper_views.py
Products/EasyNewsletter/browser/issue.py
Products/EasyNewsletter/browser/issue_online_view.pt
Products/EasyNewsletter/browser/issue_preview_view.pt
Products/EasyNewsletter/browser/issue_public_view.pt
Products/EasyNewsletter/browser/issue_send_form.pt
Products/EasyNewsletter/browser/newsletter.py
Products.EasyNewsletter-5.0.11.dist-info/LICENSE
Products.EasyNewsletter-5.0.11.dist-info/METADATA
Products.EasyNewsletter-5.0.11.dist-info/WHEEL
Products.EasyNewsletter-5.0.11.dist-info/entry_points.txt
Products.EasyNewsletter-5.0.11.dist-info/namespace_packages.txt
Products.EasyNewsletter-5.0.11.dist-info/top_level.txt
Products.EasyNewsletter-5.0.11.dist-info/RECORD
