Metadata-Version: 2.1
Name: Products.EasyNewsletter
Version: 5.0.11
Summary: Powerful newsletter/mailing addon for Plone
Home-page: https://github.com/collective/Products.EasyNewsletter
Author: Maik Derstappen (MrTango)
Author-email: md@derico.de
Maintainer: MrTango
License: GPL
Keywords: Plone Newsletter Mailing Email Mailinglist
Platform: UNKNOWN
Classifier: Development Status :: 5 - Production/Stable
Classifier: Framework :: Plone
Classifier: Framework :: Plone :: 5.2
Classifier: Programming Language :: Python
Classifier: Programming Language :: Python :: 2.7
Classifier: Programming Language :: Python :: 3.6
Classifier: Programming Language :: Python :: 3.7
Classifier: Programming Language :: Python :: 3.8
Classifier: Framework :: Plone :: Addon
Classifier: Topic :: Software Development :: Libraries :: Python Modules
Requires-Dist: Plone
Requires-Dist: Products.CMFPlone
Requires-Dist: beautifulsoup4
Requires-Dist: email-validator (>=1.1.2)
Requires-Dist: emails
Requires-Dist: html2text
Requires-Dist: jinja2
Requires-Dist: nameparser
Requires-Dist: plone.api
Requires-Dist: plone.app.registry
Requires-Dist: plone.app.upgrade
Requires-Dist: plone.protect (>=3.1.1)
Requires-Dist: plone.resource
Requires-Dist: premailer
Requires-Dist: setuptools
Requires-Dist: six
Requires-Dist: zope.formlib
Provides-Extra: test
Requires-Dist: Pillow ; extra == 'test'
Requires-Dist: isort (<5) ; extra == 'test'
Requires-Dist: pdbpp ; extra == 'test'
Requires-Dist: plone.app.contenttypes ; extra == 'test'
Requires-Dist: plone.app.robotframework[debug] ; extra == 'test'
Requires-Dist: plone.app.testing ; extra == 'test'
Requires-Dist: plone.testing ; extra == 'test'
